MANIFEST.in
README.md
setup.py
src/cmdline/__init__.py
src/cmdline/command.py
src/cmdline/config.py
src/cmdline/exceptions.py
src/cmdline/logconfig.py
src/cmdline/settings.py
src/cmdline/util.py
src/cmdline.egg-info/PKG-INFO
src/cmdline.egg-info/SOURCES.txt
src/cmdline.egg-info/dependency_links.txt
src/cmdline.egg-info/requires.txt
src/cmdline.egg-info/top_level.txt
src/tests/__init__.py
src/tests/test_config.py
src/tests/test_settings.py
src/tests/test_util.py