Metadata-Version: 2.1
Name: cmdline
Version: 0.2.0
Summary: Utilities for consistent command line tools
Home-page: http://github.com/rca/cmdline
Author: Roberto Aguilar
Author-email: r@rreboto.com
License: LICENSE
Platform: UNKNOWN
Classifier: Development Status :: 4 - Beta
Classifier: Environment :: Console
Classifier: Intended Audience :: Developers
Classifier: License :: OSI Approved :: Apache Software License
Classifier: Operating System :: OS Independent
Classifier: Programming Language :: Python
Classifier: Natural Language :: English
Classifier: Topic :: Utilities
